gava_connect/__init__.py
gava_connect/cli.py
gava_connect/kra_client.py
gava_connect-1.0.1.dist-info/licenses/LICENSE
tests/__init__.py
tests/test_kra_client.py
gava_connect-1.0.1.dist-info/METADATA
gava_connect-1.0.1.dist-info/WHEEL
gava_connect-1.0.1.dist-info/entry_points.txt
gava_connect-1.0.1.dist-info/top_level.txt
gava_connect-1.0.1.dist-info/RECORD
