Metadata-Version: 2.4
Name: gava-connect
Version: 1.0.1
Summary: A Python package for simplified access to Kenya Revenue Authority (KRA) API
Home-page: https://github.com/Paulndambo/KRA-Gava-Connect
Author: Paul Ndambo
Author-email: Paul Ndambo <paulkadabo@gmail.com>
Maintainer-email: Paul Ndambo <paulkadabo@gmail.com>
License: MIT
Project-URL: Homepage, https://github.com/Paulndambo/KRA-Gava-Connect
Project-URL: Documentation, https://github.com/Paulndambo/KRA-Gava-Connect#readme
Project-URL: Repository, https://github.com/Paulndambo/KRA-Gava-Connect
Project-URL: Bug Tracker, https://github.com/Paulndambo/KRA-Gava-Connect/issues
Keywords: kra,kenya,revenue,authority,api,tax,pin,gava
Classifier: Development Status :: 4 - Beta
Classifier: Intended Audience :: Developers
Classifier: License :: OSI Approved :: MIT License
Classifier: Operating System :: OS Independent
Classifier: Programming Language :: Python :: 3
Classifier: Programming Language :: Python :: 3.7
Classifier: Programming Language :: Python :: 3.8
Classifier: Programming Language :: Python :: 3.9
Classifier: Programming Language :: Python :: 3.10
Classifier: Programming Language :: Python :: 3.11
Classifier: Topic :: Software Development :: Libraries :: Python Modules
Classifier: Topic :: Office/Business :: Financial :: Accounting
Requires-Python: >=3.7
License-File: LICENSE
Requires-Dist: requests>=2.25.0
Requires-Dist: python-dotenv>=0.19.0
Provides-Extra: dev
Requires-Dist: pytest>=6.0; extra == "dev"
Requires-Dist: pytest-cov>=2.10; extra == "dev"
Requires-Dist: black>=21.0; extra == "dev"
Requires-Dist: flake8>=3.8; extra == "dev"
Requires-Dist: mypy>=0.800; extra == "dev"
Dynamic: author
Dynamic: home-page
Dynamic: license-file
Dynamic: requires-python
